{"dataModel":{"label":"Test emails - update","description":"lorem ipsum","type":"Data Asset","metadata":[{"namespace":"org.healthdatagateway","key":"properties/summary/title","value":"Test emails - update"},{"namespace":"org.healthdatagateway","key":"properties/summary/abstract","value":"lorem ipsum"},{"namespace":"org.healthdatagateway","key":"properties/summary/contactPoint","value":"test@test.com"},{"namespace":"org.healthdatagateway","key":"properties/summary/keywords","value":"[\"Testing\"]"},{"namespace":"org.healthdatagateway","key":"properties/provenance/temporal/startDate","value":"2022-04-21"},{"namespace":"org.healthdatagateway","key":"properties/provenance/temporal/accrualPeriodicity","value":"IRREGULAR"},{"namespace":"org.healthdatagateway","key":"properties/provenance/temporal/timeLag","value":"VARIABLE"},{"namespace":"org.healthdatagateway","key":"properties/accessibility/access/accessRights","value":"[\"http://google.como\"]"},{"namespace":"org.healthdatagateway","key":"properties/accessibility/access/jurisdiction","value":"[\"GB-ENG\"]"},{"namespace":"org.healthdatagateway","key":"properties/accessibility/access/dataController","value":"lorem ipsum"},{"namespace":"org.healthdatagateway","key":"properties/accessibility/formatAndStandards/vocabularyEncodingScheme","value":"[\"OPCS4\"]"},{"namespace":"org.healthdatagateway","key":"properties/accessibility/formatAndStandards/conformsTo","value":"[\"HL7 FHIR\"]"},{"namespace":"org.healthdatagateway","key":"properties/accessibility/formatAndStandards/language","value":"[\"aa\"]"},{"namespace":"org.healthdatagateway","key":"properties/accessibility/formatAndStandards/format","value":"[\"image\"]"},{"namespace":"org.healthdatagateway","key":"properties/observations/observations","value":"[{\"measuredValue\":\"1000\",\"observationDate\":\"22/04/2022\",\"measuredProperty\":\"Count\",\"observedNode\":\"PERSONS\"}]"},{"namespace":"org.healthdatagateway","key":"properties/summary/publisher/identifier","value":"5f89662f7150a1b050be0710"},{"namespace":"org.healthdatagateway","key":"properties/summary/publisher/name","value":"HEALTH AND SOCIAL CARE NORTHERN IRELAND"},{"namespace":"org.healthdatagateway","key":"properties/summary/publisher/memberOf","value":"ALLIANCE"}],"childDataClasses":[]}}